ocptv_ctam/__init__.py
ocptv_ctam/ctam.py
ocptv_ctam/test_hierarchy.py
ocptv_ctam/test_runner.py
ocptv_ctam/interfaces/__init__.py
ocptv_ctam/interfaces/comptool_dut.py
ocptv_ctam/interfaces/functional_ifc.py
ocptv_ctam/interfaces/fw_update_ifc.py
ocptv_ctam/interfaces/health_check_ifc.py
ocptv_ctam/interfaces/ras_ifc.py
ocptv_ctam/interfaces/telemetry_ifc.py
ocptv_ctam/interfaces/uri_builder.py
ocptv_ctam/tests/__init__.py
ocptv_ctam/tests/test_case.py
ocptv_ctam/tests/test_group.py
ocptv_ctam/tests/fw_update/__init__.py
ocptv_ctam/tests/fw_update/fw_update_group_N/_fw_update_group_N.py
ocptv_ctam/tests/fw_update/fw_update_group_N/ctam_test_full_device_update_activation_time.py
ocptv_ctam/tests/fw_update/fw_update_group_N/ctam_test_full_device_update_activation_with_failed_component.py
ocptv_ctam/tests/fw_update/fw_update_group_N/ctam_test_full_device_update_in_loop.py
ocptv_ctam/tests/fw_update/fw_update_group_N/ctam_test_full_device_update_ping_pong.py
ocptv_ctam/tests/fw_update/fw_update_group_N/ctam_test_full_device_update_rollback.py
ocptv_ctam/tests/fw_update/fw_update_group_N/ctam_test_full_device_update_staging_interruption_with_single_device_update.py
ocptv_ctam/tests/fw_update/fw_update_group_N/ctam_test_full_device_update_staging_time.py
ocptv_ctam/tests/fw_update/fw_update_group_N/ctam_test_full_device_update_staging_with_failed_component.py
ocptv_ctam/tests/fw_update/fw_update_group_N/ctam_test_full_device_update_with_older_version.py
ocptv_ctam/tests/fw_update/fw_update_group_N/ctam_test_full_device_update_with_self_test.py
ocptv_ctam/tests/fw_update/fw_update_group_N/ctam_test_negative_corrupt_image_update.py
ocptv_ctam/tests/fw_update/fw_update_group_N/ctam_test_negative_empty_metadata_image_update.py
ocptv_ctam/tests/fw_update/fw_update_group_N/ctam_test_negative_invalid_signed_image_update.py
ocptv_ctam/tests/fw_update/fw_update_group_N/ctam_test_negative_invalid_uuid_image_update.py
ocptv_ctam-0.0.1.dist-info/LICENSE
ocptv_ctam-0.0.1.dist-info/METADATA
ocptv_ctam-0.0.1.dist-info/WHEEL
ocptv_ctam-0.0.1.dist-info/entry_points.txt
ocptv_ctam-0.0.1.dist-info/top_level.txt
ocptv_ctam-0.0.1.dist-info/RECORD
