Metadata-Version: 2.1
Name: ocptv-ctam
Version: 0.0.1
Summary: Compliance Tool for Accelerator Management
Author-email: OCP Test & Validation <ocp-test-validation@OCP-All.groups.io>
License: MIT License
Project-URL: Homepage, https://github.com/opencomputeproject/ocp-diag-ctam
Project-URL: Bug reports, https://github.com/opencomputeproject/ocp-diag-ctam/issues
Project-URL: Source, https://github.com/opencomputeproject/ocp-diag-ctam
Keywords: ocp,ocptv,accelerator,compliance
Classifier: License :: OSI Approved :: MIT License
Classifier: Programming Language :: Python
Classifier: Programming Language :: Python :: 3.10
Classifier: Programming Language :: Python :: 3.11
Classifier: Topic :: System :: Hardware
Requires-Python: >=3.10
License-File: LICENSE
Requires-Dist: ocptv
Requires-Dist: prettytable
Requires-Dist: redfish
Requires-Dist: requests
Requires-Dist: requests-ntlm
Requires-Dist: requests-toolbelt
Requires-Dist: requests-unixsocket
Requires-Dist: alive-progress >=3.1.4
Provides-Extra: dev
Requires-Dist: black ; extra == 'dev'
Requires-Dist: bumpver ; extra == 'dev'
Requires-Dist: isort ; extra == 'dev'
